bindcompare/__init__.py
bindcompare/bcapp.py
bindcompare/bindcompare.py
bindcompare/comparexp.py
bindcompare/explore.py
bindcompare/retrieve.py
bindcompare/bindapp/__init__.py
bindcompare/bindapp/downstream.py
bindcompare/bindapp/exp_class.py
bindcompare/bindapp/help_dict.py
bindcompare/bindapp/merge.py
bindcompare/bindapp/merge_class.py
bindcompare/bindapp/utils.py
bindcompare/reference_files/dm6.fa.fai
bindcompare/reference_files/dm6.fa.gz
bindcompare/reference_files/dmel-all-r6.46.gtf.gz
bindcompare-2.0.0.dist-info/LICENSE
bindcompare-2.0.0.dist-info/METADATA
bindcompare-2.0.0.dist-info/WHEEL
bindcompare-2.0.0.dist-info/entry_points.txt
bindcompare-2.0.0.dist-info/top_level.txt
bindcompare-2.0.0.dist-info/RECORD
