Metadata-Version: 2.1
Name: bindcompare
Version: 2.0.0
Summary: A Novel DNA/RNA Binding Integration and Analysis Platform.
Home-page: https://github.com/pranavmahabs/bindcompare
Author: P. Mahableshwarkar, M.Ray, E. Larschan 2024
Author-email: pranav_mahableshwarkar@brown.edu
License: GPL
Classifier: Development Status :: 5 - Production/Stable
Classifier: Intended Audience :: Science/Research
Classifier: License :: OSI Approved :: GNU General Public License v3 (GPLv3)
Classifier: Operating System :: OS Independent
Classifier: Programming Language :: Python
License-File: LICENSE
Requires-Dist: numpy >=1.0
Requires-Dist: pandas >=1.0
Requires-Dist: customtkinter >=1.0
Requires-Dist: matplotlib >=3.0
Requires-Dist: biopython >=1.0
Requires-Dist: intervaltree >=1.0
Requires-Dist: matplotlib-venn >=0.11
Requires-Dist: scipy >=1.0
